invertedai_simulate/__init__.py
invertedai_simulate/dataset/__init__.py
invertedai_simulate/dataset/db.py
invertedai_simulate/dataset/env_dataset.py
invertedai_simulate/dataset/models.py
invertedai_simulate/interface.py
invertedai_simulate/utils.py
invertedai_simulate/zmq_client.py
invertedai_simulate-1.0.5.dist-info/LICENSE
invertedai_simulate-1.0.5.dist-info/WHEEL
invertedai_simulate-1.0.5.dist-info/METADATA
invertedai_simulate-1.0.5.dist-info/RECORD
